apyck/__init__.py
apyck/uuid.cp310-win_amd64.pyd
apyck-0.1.22.323b0.dist-info/LICENSE
apyck-0.1.22.323b0.dist-info/METADATA
apyck-0.1.22.323b0.dist-info/WHEEL
apyck-0.1.22.323b0.dist-info/top_level.txt
apyck-0.1.22.323b0.dist-info/RECORD
