Metadata-Version: 2.1
Name: apyck
Version: 0.1.22.323.beta
Summary: A package for developing fintech systems.
Home-page: https://pypi.org/project/apyck
Author: EGOPY
Author-email: 
License: BSD
Keywords: quant investment quantitative trading algotrading
Platform: UNKNOWN
Classifier: Operating System :: Microsoft :: Windows
Classifier: Operating System :: POSIX :: Linux
Classifier: Programming Language :: Python
Classifier: Programming Language :: Cython
Classifier: Programming Language :: C
Classifier: Topic :: Office/Business :: Financial
Classifier: Topic :: Scientific/Engineering :: Mathematics
Classifier: License :: OSI Approved :: BSD License
Requires-Python: >=3.10
License-File: LICENSE
